afar/__init__.py
afar/_abra.py
afar/_core.py
afar/_exceptions.py
afar/_inspect.py
afar/_magic.py
afar/_printing.py
afar/_reprs.py
afar/_utils.py
afar/_version.py
afar/_where.py
afar/tests/__init__.py
afar/tests/test_core.py
afar/tests/test_later.py
afar/tests/test_remotely.py
afar-0.6.1.dist-info/LICENSE
afar-0.6.1.dist-info/METADATA
afar-0.6.1.dist-info/WHEEL
afar-0.6.1.dist-info/top_level.txt
afar-0.6.1.dist-info/RECORD
