Metadata-Version: 2.1
Name: afar
Version: 0.6.1
Summary: Run code on a Dask cluster via a context manager or IPython magic
Home-page: https://github.com/eriknw/afar
Author: Erik Welch
Author-email: erik.n.welch@gmail.com
License: BSD
Platform: UNKNOWN
Classifier: Development Status :: 3 - Alpha
Classifier: License :: OSI Approved :: BSD License
Classifier: Operating System :: OS Independent
Classifier: Programming Language :: Python
Classifier: Programming Language :: Python :: 3
Classifier: Programming Language :: Python :: 3.7
Classifier: Programming Language :: Python :: 3.8
Classifier: Programming Language :: Python :: 3.9
Classifier: Programming Language :: Python :: 3 :: Only
Classifier: Programming Language :: Python :: Implementation :: CPython
Requires-Python: >=3.7
License-File: LICENSE
Requires-Dist: innerscope
Requires-Dist: distributed (>=2021.9.1)
